apldx_test/__init__.py
apldx_test/apldx_test.py
apldx_test-0.0.2.data/scripts/hello-apldx_test
apldx_test-0.0.2.dist-info/METADATA
apldx_test-0.0.2.dist-info/RECORD
apldx_test-0.0.2.dist-info/WHEEL
apldx_test-0.0.2.dist-info/entry_points.txt
apldx_test-0.0.2.dist-info/top_level.txt
