Metadata-Version: 2.1
Name: apldx-test
Version: 0.0.2
Summary: apldx_test - Test to delete and remake package
Home-page: UNKNOWN
Author: 
Author-email: 
License: MIT
Platform: UNKNOWN
Provides-Extra: dev
Provides-Extra: dev
Requires-Dist: pytest; extra == 'dev'
Requires-Dist: tox; extra == 'dev'
